Metadata-Version: 2.4
Name: django-cities-xtd
Version: 0.7.1
Summary: Place models and worldwide place data for Django
Author-email: Arthur Hanson <worldnomad@gmail.com>, Ben Dowling <ben.m.dowling@gmail.com>
License: MIT
Project-URL: Homepage, https://github.com/arthanson/django-cities-xtd
Keywords: django,cities,countries,regions,postal codes,geonames
Classifier: Development Status :: 4 - Beta
Classifier: Environment :: Web Environment
Classifier: Framework :: Django
Classifier: Framework :: Django :: 5.0
Classifier: Framework :: Django :: 5.1
Classifier: Framework :: Django :: 5.2
Classifier: Intended Audience :: Developers
Classifier: License :: OSI Approved :: MIT License
Classifier: Operating System :: OS Independent
Classifier: Programming Language :: Python
Classifier: Programming Language :: Python :: 3.10
Classifier: Programming Language :: Python :: 3.11
Classifier: Programming Language :: Python :: 3.12
Classifier: Programming Language :: Python :: 3.13
Classifier: Programming Language :: Python :: 3.14
Classifier: Topic :: Internet :: WWW/HTTP
Classifier: Topic :: Software Development :: Libraries :: Python Modules
Requires-Python: >=3.10
License-File: LICENSE
Requires-Dist: Django>=5.0
Requires-Dist: django-model-utils>=5.0.0
Requires-Dist: swapper>=1.3.0
Requires-Dist: tqdm>=4.0.0
Provides-Extra: test
Requires-Dist: psycopg[binary]>=3.0; extra == "test"
Requires-Dist: tox>=4.0; extra == "test"
Dynamic: license-file
